yt_idefix/__init__.py
yt_idefix/api.py
yt_idefix/data_structures.py
yt_idefix/definitions.py
yt_idefix/fields.py
yt_idefix/io.py
yt_idefix/misc.py
yt_idefix/py.typed
yt_idefix/_io/C_io.py
yt_idefix/_io/__init__.py
yt_idefix/_io/commons.py
yt_idefix/_io/dmp_io.py
yt_idefix/_io/h5_io.py
yt_idefix/_io/vtk_io.py
yt_idefix-2.4.1.dist-info/METADATA
yt_idefix-2.4.1.dist-info/WHEEL
yt_idefix-2.4.1.dist-info/entry_points.txt
yt_idefix-2.4.1.dist-info/licenses/LICENSE
yt_idefix-2.4.1.dist-info/RECORD
