Metadata-Version: 2.4
Name: yt_idefix
Version: 2.4.1
Summary: An extension module for yt, adding a frontend for Idefix and Pluto
Project-URL: Homepage, https://yt-project.org/
Project-URL: Documentation, https://yt-project.org/docs/dev/
Project-URL: Source, https://github.com/neutrinoceros/yt_idefix
Project-URL: Tracker, https://github.com/neutrinoceros/yt_idefix/issues
Author: C.M.T. Robert
License: GPL-3.0
License-File: LICENSE
Keywords: astronomy astrophysics visualization amr adaptivemeshrefinement
Classifier: Development Status :: 5 - Production/Stable
Classifier: Environment :: Console
Classifier: Framework :: Matplotlib
Classifier: Intended Audience :: Science/Research
Classifier: License :: OSI Approved :: GNU General Public License v3 (GPLv3)
Classifier: Operating System :: MacOS :: MacOS X
Classifier: Operating System :: POSIX :: AIX
Classifier: Operating System :: POSIX :: Linux
Classifier: Programming Language :: Python :: 3
Classifier: Topic :: Scientific/Engineering :: Astronomy
Classifier: Topic :: Scientific/Engineering :: Physics
Classifier: Topic :: Scientific/Engineering :: Visualization
Classifier: Typing :: Typed
Requires-Python: >=3.10
Requires-Dist: inifix>=4.1.0
Requires-Dist: numpy>=1.21.2
Requires-Dist: typing-extensions>=4.4.0; python_version < '3.12'
Requires-Dist: yt>=4.2.0
Provides-Extra: hdf5
Requires-Dist: h5py>=3.7.0; extra == 'hdf5'
